sanic_testing/__init__.py
sanic_testing/manager.py
sanic_testing/reusable.py
sanic_testing/testing.py
sanic_testing/websocket.py
sanic_testing-24.6.0.dist-info/LICENSE
sanic_testing-24.6.0.dist-info/METADATA
sanic_testing-24.6.0.dist-info/WHEEL
sanic_testing-24.6.0.dist-info/top_level.txt
sanic_testing-24.6.0.dist-info/RECORD
