Metadata-Version: 2.1
Name: sanic-testing
Version: 24.6.0
Summary: Core testing clients for Sanic
Home-page: https://github.com/sanic-org/sanic-testing/
Author: Adam Hopkins
Author-email: admhpkns@gmail.com
License: MIT
Platform: any
Classifier: Development Status :: 4 - Beta
Classifier: Environment :: Web Environment
Classifier: License :: OSI Approved :: MIT License
Classifier: Programming Language :: Python :: 3.8
Classifier: Programming Language :: Python :: 3.9
Classifier: Programming Language :: Python :: 3.10
Classifier: Programming Language :: Python :: 3.11
Classifier: Programming Language :: Python :: 3.12
License-File: LICENSE
Requires-Dist: httpx>=0.18
Provides-Extra: dev
Requires-Dist: pytest; extra == "dev"
Requires-Dist: sanic>=22.12; extra == "dev"
Requires-Dist: pytest-asyncio; extra == "dev"
Requires-Dist: setuptools; python_version > "3.11" and extra == "dev"
